{
  "CodigoSerie": "IPC264455",
  "Slug": "comunidades-y-ciudades-autonomas-asturias-principado-de/grupos-especiales-2001-productos-energeticos",
  "IdTabla": 50916,
  "Tabla": {
    "CodigoOperacion": "IPC",
    "IdTabla": 50916,
    "Tabla": "\u00CDndices por comunidades aut\u00F3nomas de grupos especiales",
    "CodigoTabla": "2021_NAC-CCAA",
    "Dim0": "Comunidades y Ciudades Aut\u00F3nomas",
    "Dim1": "Grupos especiales 2001",
    "Dim2": "Tipo de dato",
    "Valor2": "\u00CDndice",
    "Escala": "-",
    "Unidad": "\u00CDndice",
    "Clasificacion": "Base 2021 (IPC)",
    "NumSeries": 551
  },
  "Base": "Base 2021 (IPC)",
  "TipoDato": "\u00CDndice",
  "Unidad": "\u00CDndice",
  "Territorialidad": "Comunidades y Ciudades Aut\u00F3nomas",
  "Territorio": "Asturias, Principado de",
  "ECOICOP": "Grupos especiales 2001",
  "DetalleECOICOP": "Productos energ\u00E9ticos",
  "Serie": "Asturias, Principado de. Productos energ\u00E9ticos. \u00CDndice. ",
  "Escala": "-",
  "Datos": [
    {
      "CodigoPeriodo": "200201",
      "TipoDato": "Definitivo",
      "Indice": 51.5390000000,
      "VariacionMensual": null,
      "VariacionAnual": null
    },
    {
      "CodigoPeriodo": "200202",
      "TipoDato": "Definitivo",
      "Indice": 51.6210000000,
      "VariacionMensual": 0.00159,
      "VariacionAnual": null
    },
    {
      "CodigoPeriodo": "200203",
      "TipoDato": "Definitivo",
      "Indice": 52.6360000000,
      "VariacionMensual": 0.01966,
      "VariacionAnual": null
    },
    {
      "CodigoPeriodo": "200204",
      "TipoDato": "Definitivo",
      "Indice": 54.0700000000,
      "VariacionMensual": 0.02724,
      "VariacionAnual": null
    },
    {
      "CodigoPeriodo": "200205",
      "TipoDato": "Definitivo",
      "Indice": 54.1680000000,
      "VariacionMensual": 0.00181,
      "VariacionAnual": null
    },
    {
      "CodigoPeriodo": "200206",
      "TipoDato": "Definitivo",
      "Indice": 53.1470000000,
      "VariacionMensual": -0.01885,
      "VariacionAnual": null
    },
    {
      "CodigoPeriodo": "200207",
      "TipoDato": "Definitivo",
      "Indice": 53.2930000000,
      "VariacionMensual": 0.00275,
      "VariacionAnual": null
    },
    {
      "CodigoPeriodo": "200208",
      "TipoDato": "Definitivo",
      "Indice": 53.3980000000,
      "VariacionMensual": 0.00197,
      "VariacionAnual": null
    },
    {
      "CodigoPeriodo": "200209",
      "TipoDato": "Definitivo",
      "Indice": 53.8470000000,
      "VariacionMensual": 0.00841,
      "VariacionAnual": null
    },
    {
      "CodigoPeriodo": "200210",
      "TipoDato": "Definitivo",
      "Indice": 54.2750000000,
      "VariacionMensual": 0.00795,
      "VariacionAnual": null
    },
    {
      "CodigoPeriodo": "200211",
      "TipoDato": "Definitivo",
      "Indice": 52.7900000000,
      "VariacionMensual": -0.02736,
      "VariacionAnual": null
    },
    {
      "CodigoPeriodo": "200212",
      "TipoDato": "Definitivo",
      "Indice": 53.3890000000,
      "VariacionMensual": 0.01135,
      "VariacionAnual": null
    },
    {
      "CodigoPeriodo": "200301",
      "TipoDato": "Definitivo",
      "Indice": 54.5060000000,
      "VariacionMensual": 0.02092,
      "VariacionAnual": 0.05757
    },
    {
      "CodigoPeriodo": "200302",
      "TipoDato": "Definitivo",
      "Indice": 55.4330000000,
      "VariacionMensual": 0.01701,
      "VariacionAnual": 0.07385
    },
    {
      "CodigoPeriodo": "200303",
      "TipoDato": "Definitivo",
      "Indice": 56.2180000000,
      "VariacionMensual": 0.01416,
      "VariacionAnual": 0.06805
    },
    {
      "CodigoPeriodo": "200304",
      "TipoDato": "Definitivo",
      "Indice": 54.5610000000,
      "VariacionMensual": -0.02947,
      "VariacionAnual": 0.00908
    },
    {
      "CodigoPeriodo": "200305",
      "TipoDato": "Definitivo",
      "Indice": 53.1300000000,
      "VariacionMensual": -0.02623,
      "VariacionAnual": -0.01916
    },
    {
      "CodigoPeriodo": "200306",
      "TipoDato": "Definitivo",
      "Indice": 52.8090000000,
      "VariacionMensual": -0.00604,
      "VariacionAnual": -0.00636
    },
    {
      "CodigoPeriodo": "200307",
      "TipoDato": "Definitivo",
      "Indice": 53.3040000000,
      "VariacionMensual": 0.00937,
      "VariacionAnual": 0.00021
    },
    {
      "CodigoPeriodo": "200308",
      "TipoDato": "Definitivo",
      "Indice": 54.0690000000,
      "VariacionMensual": 0.01435,
      "VariacionAnual": 0.01257
    },
    {
      "CodigoPeriodo": "200309",
      "TipoDato": "Definitivo",
      "Indice": 53.8500000000,
      "VariacionMensual": -0.00405,
      "VariacionAnual": 0.00006
    },
    {
      "CodigoPeriodo": "200310",
      "TipoDato": "Definitivo",
      "Indice": 53.3110000000,
      "VariacionMensual": -0.01001,
      "VariacionAnual": -0.01776
    },
    {
      "CodigoPeriodo": "200311",
      "TipoDato": "Definitivo",
      "Indice": 53.4940000000,
      "VariacionMensual": 0.00343,
      "VariacionAnual": 0.01334
    },
    {
      "CodigoPeriodo": "200312",
      "TipoDato": "Definitivo",
      "Indice": 53.3080000000,
      "VariacionMensual": -0.00348,
      "VariacionAnual": -0.00152
    },
    {
      "CodigoPeriodo": "200401",
      "TipoDato": "Definitivo",
      "Indice": 54.1340000000,
      "VariacionMensual": 0.01549,
      "VariacionAnual": -0.00682
    },
    {
      "CodigoPeriodo": "200402",
      "TipoDato": "Definitivo",
      "Indice": 54.4690000000,
      "VariacionMensual": 0.00619,
      "VariacionAnual": -0.01739
    },
    {
      "CodigoPeriodo": "200403",
      "TipoDato": "Definitivo",
      "Indice": 55.1540000000,
      "VariacionMensual": 0.01258,
      "VariacionAnual": -0.01893
    },
    {
      "CodigoPeriodo": "200404",
      "TipoDato": "Definitivo",
      "Indice": 55.9590000000,
      "VariacionMensual": 0.01460,
      "VariacionAnual": 0.02562
    },
    {
      "CodigoPeriodo": "200405",
      "TipoDato": "Definitivo",
      "Indice": 57.3520000000,
      "VariacionMensual": 0.02489,
      "VariacionAnual": 0.07947
    },
    {
      "CodigoPeriodo": "200406",
      "TipoDato": "Definitivo",
      "Indice": 57.5380000000,
      "VariacionMensual": 0.00324,
      "VariacionAnual": 0.08955
    },
    {
      "CodigoPeriodo": "200407",
      "TipoDato": "Definitivo",
      "Indice": 57.6390000000,
      "VariacionMensual": 0.00176,
      "VariacionAnual": 0.08133
    },
    {
      "CodigoPeriodo": "200408",
      "TipoDato": "Definitivo",
      "Indice": 58.5930000000,
      "VariacionMensual": 0.01655,
      "VariacionAnual": 0.08367
    },
    {
      "CodigoPeriodo": "200409",
      "TipoDato": "Definitivo",
      "Indice": 58.6800000000,
      "VariacionMensual": 0.00148,
      "VariacionAnual": 0.08969
    },
    {
      "CodigoPeriodo": "200410",
      "TipoDato": "Definitivo",
      "Indice": 60.2840000000,
      "VariacionMensual": 0.02733,
      "VariacionAnual": 0.13080
    },
    {
      "CodigoPeriodo": "200411",
      "TipoDato": "Definitivo",
      "Indice": 59.7570000000,
      "VariacionMensual": -0.00874,
      "VariacionAnual": 0.11708
    },
    {
      "CodigoPeriodo": "200412",
      "TipoDato": "Definitivo",
      "Indice": 58.1090000000,
      "VariacionMensual": -0.02758,
      "VariacionAnual": 0.09006
    },
    {
      "CodigoPeriodo": "200501",
      "TipoDato": "Definitivo",
      "Indice": 57.5410000000,
      "VariacionMensual": -0.00977,
      "VariacionAnual": 0.06294
    },
    {
      "CodigoPeriodo": "200502",
      "TipoDato": "Definitivo",
      "Indice": 58.6910000000,
      "VariacionMensual": 0.01999,
      "VariacionAnual": 0.07751
    },
    {
      "CodigoPeriodo": "200503",
      "TipoDato": "Definitivo",
      "Indice": 59.9530000000,
      "VariacionMensual": 0.02150,
      "VariacionAnual": 0.08701
    },
    {
      "CodigoPeriodo": "200504",
      "TipoDato": "Definitivo",
      "Indice": 61.4170000000,
      "VariacionMensual": 0.02442,
      "VariacionAnual": 0.09754
    },
    {
      "CodigoPeriodo": "200505",
      "TipoDato": "Definitivo",
      "Indice": 61.3360000000,
      "VariacionMensual": -0.00132,
      "VariacionAnual": 0.06947
    },
    {
      "CodigoPeriodo": "200506",
      "TipoDato": "Definitivo",
      "Indice": 62.0810000000,
      "VariacionMensual": 0.01215,
      "VariacionAnual": 0.07896
    },
    {
      "CodigoPeriodo": "200507",
      "TipoDato": "Definitivo",
      "Indice": 64.2320000000,
      "VariacionMensual": 0.03465,
      "VariacionAnual": 0.11438
    },
    {
      "CodigoPeriodo": "200508",
      "TipoDato": "Definitivo",
      "Indice": 65.3360000000,
      "VariacionMensual": 0.01719,
      "VariacionAnual": 0.11508
    },
    {
      "CodigoPeriodo": "200509",
      "TipoDato": "Definitivo",
      "Indice": 67.4970000000,
      "VariacionMensual": 0.03308,
      "VariacionAnual": 0.15026
    },
    {
      "CodigoPeriodo": "200510",
      "TipoDato": "Definitivo",
      "Indice": 67.0310000000,
      "VariacionMensual": -0.00690,
      "VariacionAnual": 0.11192
    },
    {
      "CodigoPeriodo": "200511",
      "TipoDato": "Definitivo",
      "Indice": 65.2170000000,
      "VariacionMensual": -0.02706,
      "VariacionAnual": 0.09137
    },
    {
      "CodigoPeriodo": "200512",
      "TipoDato": "Definitivo",
      "Indice": 64.0500000000,
      "VariacionMensual": -0.01789,
      "VariacionAnual": 0.10224
    },
    {
      "CodigoPeriodo": "200601",
      "TipoDato": "Definitivo",
      "Indice": 65.9600000000,
      "VariacionMensual": 0.02982,
      "VariacionAnual": 0.14631
    },
    {
      "CodigoPeriodo": "200602",
      "TipoDato": "Definitivo",
      "Indice": 66.4450000000,
      "VariacionMensual": 0.00735,
      "VariacionAnual": 0.13212
    },
    {
      "CodigoPeriodo": "200603",
      "TipoDato": "Definitivo",
      "Indice": 66.7850000000,
      "VariacionMensual": 0.00512,
      "VariacionAnual": 0.11396
    },
    {
      "CodigoPeriodo": "200604",
      "TipoDato": "Definitivo",
      "Indice": 68.7550000000,
      "VariacionMensual": 0.02950,
      "VariacionAnual": 0.11948
    },
    {
      "CodigoPeriodo": "200605",
      "TipoDato": "Definitivo",
      "Indice": 69.9350000000,
      "VariacionMensual": 0.01716,
      "VariacionAnual": 0.14019
    },
    {
      "CodigoPeriodo": "200606",
      "TipoDato": "Definitivo",
      "Indice": 69.3890000000,
      "VariacionMensual": -0.00781,
      "VariacionAnual": 0.11772
    },
    {
      "CodigoPeriodo": "200607",
      "TipoDato": "Definitivo",
      "Indice": 70.3470000000,
      "VariacionMensual": 0.01381,
      "VariacionAnual": 0.09520
    },
    {
      "CodigoPeriodo": "200608",
      "TipoDato": "Definitivo",
      "Indice": 70.4770000000,
      "VariacionMensual": 0.00185,
      "VariacionAnual": 0.07869
    },
    {
      "CodigoPeriodo": "200609",
      "TipoDato": "Definitivo",
      "Indice": 67.8720000000,
      "VariacionMensual": -0.03696,
      "VariacionAnual": 0.00556
    },
    {
      "CodigoPeriodo": "200610",
      "TipoDato": "Definitivo",
      "Indice": 65.4880000000,
      "VariacionMensual": -0.03512,
      "VariacionAnual": -0.02302
    },
    {
      "CodigoPeriodo": "200611",
      "TipoDato": "Definitivo",
      "Indice": 65.0160000000,
      "VariacionMensual": -0.00721,
      "VariacionAnual": -0.00308
    },
    {
      "CodigoPeriodo": "200612",
      "TipoDato": "Definitivo",
      "Indice": 65.2530000000,
      "VariacionMensual": 0.00365,
      "VariacionAnual": 0.01878
    },
    {
      "CodigoPeriodo": "200701",
      "TipoDato": "Definitivo",
      "Indice": 64.9870000000,
      "VariacionMensual": -0.00408,
      "VariacionAnual": -0.01475
    },
    {
      "CodigoPeriodo": "200702",
      "TipoDato": "Definitivo",
      "Indice": 65.0840000000,
      "VariacionMensual": 0.00149,
      "VariacionAnual": -0.02048
    },
    {
      "CodigoPeriodo": "200703",
      "TipoDato": "Definitivo",
      "Indice": 66.3610000000,
      "VariacionMensual": 0.01962,
      "VariacionAnual": -0.00635
    },
    {
      "CodigoPeriodo": "200704",
      "TipoDato": "Definitivo",
      "Indice": 67.5760000000,
      "VariacionMensual": 0.01831,
      "VariacionAnual": -0.01715
    },
    {
      "CodigoPeriodo": "200705",
      "TipoDato": "Definitivo",
      "Indice": 68.5630000000,
      "VariacionMensual": 0.01461,
      "VariacionAnual": -0.01962
    },
    {
      "CodigoPeriodo": "200706",
      "TipoDato": "Definitivo",
      "Indice": 69.0410000000,
      "VariacionMensual": 0.00697,
      "VariacionAnual": -0.00502
    },
    {
      "CodigoPeriodo": "200707",
      "TipoDato": "Definitivo",
      "Indice": 69.3430000000,
      "VariacionMensual": 0.00437,
      "VariacionAnual": -0.01427
    },
    {
      "CodigoPeriodo": "200708",
      "TipoDato": "Definitivo",
      "Indice": 68.8030000000,
      "VariacionMensual": -0.00779,
      "VariacionAnual": -0.02375
    },
    {
      "CodigoPeriodo": "200709",
      "TipoDato": "Definitivo",
      "Indice": 69.2280000000,
      "VariacionMensual": 0.00618,
      "VariacionAnual": 0.01998
    },
    {
      "CodigoPeriodo": "200710",
      "TipoDato": "Definitivo",
      "Indice": 69.8790000000,
      "VariacionMensual": 0.00940,
      "VariacionAnual": 0.06705
    },
    {
      "CodigoPeriodo": "200711",
      "TipoDato": "Definitivo",
      "Indice": 71.7780000000,
      "VariacionMensual": 0.02718,
      "VariacionAnual": 0.10401
    },
    {
      "CodigoPeriodo": "200712",
      "TipoDato": "Definitivo",
      "Indice": 72.5920000000,
      "VariacionMensual": 0.01134,
      "VariacionAnual": 0.11247
    },
    {
      "CodigoPeriodo": "200801",
      "TipoDato": "Definitivo",
      "Indice": 73.6280000000,
      "VariacionMensual": 0.01427,
      "VariacionAnual": 0.13297
    },
    {
      "CodigoPeriodo": "200802",
      "TipoDato": "Definitivo",
      "Indice": 73.7400000000,
      "VariacionMensual": 0.00152,
      "VariacionAnual": 0.13300
    },
    {
      "CodigoPeriodo": "200803",
      "TipoDato": "Definitivo",
      "Indice": 75.8510000000,
      "VariacionMensual": 0.02863,
      "VariacionAnual": 0.14301
    },
    {
      "CodigoPeriodo": "200804",
      "TipoDato": "Definitivo",
      "Indice": 76.7030000000,
      "VariacionMensual": 0.01123,
      "VariacionAnual": 0.13506
    },
    {
      "CodigoPeriodo": "200805",
      "TipoDato": "Definitivo",
      "Indice": 80.0560000000,
      "VariacionMensual": 0.04371,
      "VariacionAnual": 0.16763
    },
    {
      "CodigoPeriodo": "200806",
      "TipoDato": "Definitivo",
      "Indice": 82.5370000000,
      "VariacionMensual": 0.03099,
      "VariacionAnual": 0.19548
    },
    {
      "CodigoPeriodo": "200807",
      "TipoDato": "Definitivo",
      "Indice": 84.3950000000,
      "VariacionMensual": 0.02251,
      "VariacionAnual": 0.21707
    },
    {
      "CodigoPeriodo": "200808",
      "TipoDato": "Definitivo",
      "Indice": 80.9430000000,
      "VariacionMensual": -0.04090,
      "VariacionAnual": 0.17645
    },
    {
      "CodigoPeriodo": "200809",
      "TipoDato": "Definitivo",
      "Indice": 79.5450000000,
      "VariacionMensual": -0.01727,
      "VariacionAnual": 0.14903
    },
    {
      "CodigoPeriodo": "200810",
      "TipoDato": "Definitivo",
      "Indice": 76.4560000000,
      "VariacionMensual": -0.03883,
      "VariacionAnual": 0.09412
    },
    {
      "CodigoPeriodo": "200811",
      "TipoDato": "Definitivo",
      "Indice": 71.4890000000,
      "VariacionMensual": -0.06497,
      "VariacionAnual": -0.00403
    },
    {
      "CodigoPeriodo": "200812",
      "TipoDato": "Definitivo",
      "Indice": 67.3620000000,
      "VariacionMensual": -0.05773,
      "VariacionAnual": -0.07205
    },
    {
      "CodigoPeriodo": "200901",
      "TipoDato": "Definitivo",
      "Indice": 66.8050000000,
      "VariacionMensual": -0.00827,
      "VariacionAnual": -0.09267
    },
    {
      "CodigoPeriodo": "200902",
      "TipoDato": "Definitivo",
      "Indice": 67.6440000000,
      "VariacionMensual": 0.01256,
      "VariacionAnual": -0.08267
    },
    {
      "CodigoPeriodo": "200903",
      "TipoDato": "Definitivo",
      "Indice": 66.9140000000,
      "VariacionMensual": -0.01079,
      "VariacionAnual": -0.11782
    },
    {
      "CodigoPeriodo": "200904",
      "TipoDato": "Definitivo",
      "Indice": 67.0550000000,
      "VariacionMensual": 0.00211,
      "VariacionAnual": -0.12578
    },
    {
      "CodigoPeriodo": "200905",
      "TipoDato": "Definitivo",
      "Indice": 67.6950000000,
      "VariacionMensual": 0.00954,
      "VariacionAnual": -0.15440
    },
    {
      "CodigoPeriodo": "200906",
      "TipoDato": "Definitivo",
      "Indice": 70.6180000000,
      "VariacionMensual": 0.04318,
      "VariacionAnual": -0.14441
    },
    {
      "CodigoPeriodo": "200907",
      "TipoDato": "Definitivo",
      "Indice": 70.7230000000,
      "VariacionMensual": 0.00149,
      "VariacionAnual": -0.16200
    },
    {
      "CodigoPeriodo": "200908",
      "TipoDato": "Definitivo",
      "Indice": 72.5170000000,
      "VariacionMensual": 0.02537,
      "VariacionAnual": -0.10410
    },
    {
      "CodigoPeriodo": "200909",
      "TipoDato": "Definitivo",
      "Indice": 71.2260000000,
      "VariacionMensual": -0.01780,
      "VariacionAnual": -0.10458
    },
    {
      "CodigoPeriodo": "200910",
      "TipoDato": "Definitivo",
      "Indice": 71.3640000000,
      "VariacionMensual": 0.00194,
      "VariacionAnual": -0.06660
    },
    {
      "CodigoPeriodo": "200911",
      "TipoDato": "Definitivo",
      "Indice": 72.8370000000,
      "VariacionMensual": 0.02064,
      "VariacionAnual": 0.01886
    },
    {
      "CodigoPeriodo": "200912",
      "TipoDato": "Definitivo",
      "Indice": 72.4200000000,
      "VariacionMensual": -0.00573,
      "VariacionAnual": 0.07509
    },
    {
      "CodigoPeriodo": "201001",
      "TipoDato": "Definitivo",
      "Indice": 74.3780000000,
      "VariacionMensual": 0.02704,
      "VariacionAnual": 0.11336
    },
    {
      "CodigoPeriodo": "201002",
      "TipoDato": "Definitivo",
      "Indice": 74.3680000000,
      "VariacionMensual": -0.00013,
      "VariacionAnual": 0.09940
    },
    {
      "CodigoPeriodo": "201003",
      "TipoDato": "Definitivo",
      "Indice": 76.2170000000,
      "VariacionMensual": 0.02486,
      "VariacionAnual": 0.13903
    },
    {
      "CodigoPeriodo": "201004",
      "TipoDato": "Definitivo",
      "Indice": 78.2520000000,
      "VariacionMensual": 0.02670,
      "VariacionAnual": 0.16698
    },
    {
      "CodigoPeriodo": "201005",
      "TipoDato": "Definitivo",
      "Indice": 78.8750000000,
      "VariacionMensual": 0.00796,
      "VariacionAnual": 0.16515
    },
    {
      "CodigoPeriodo": "201006",
      "TipoDato": "Definitivo",
      "Indice": 78.3820000000,
      "VariacionMensual": -0.00625,
      "VariacionAnual": 0.10994
    },
    {
      "CodigoPeriodo": "201007",
      "TipoDato": "Definitivo",
      "Indice": 79.0360000000,
      "VariacionMensual": 0.00834,
      "VariacionAnual": 0.11754
    },
    {
      "CodigoPeriodo": "201008",
      "TipoDato": "Definitivo",
      "Indice": 78.6940000000,
      "VariacionMensual": -0.00433,
      "VariacionAnual": 0.08518
    },
    {
      "CodigoPeriodo": "201009",
      "TipoDato": "Definitivo",
      "Indice": 79.0030000000,
      "VariacionMensual": 0.00393,
      "VariacionAnual": 0.10919
    },
    {
      "CodigoPeriodo": "201010",
      "TipoDato": "Definitivo",
      "Indice": 80.1780000000,
      "VariacionMensual": 0.01487,
      "VariacionAnual": 0.12351
    },
    {
      "CodigoPeriodo": "201011",
      "TipoDato": "Definitivo",
      "Indice": 81.2660000000,
      "VariacionMensual": 0.01357,
      "VariacionAnual": 0.11572
    },
    {
      "CodigoPeriodo": "201012",
      "TipoDato": "Definitivo",
      "Indice": 83.5590000000,
      "VariacionMensual": 0.02822,
      "VariacionAnual": 0.15381
    },
    {
      "CodigoPeriodo": "201101",
      "TipoDato": "Definitivo",
      "Indice": 87.3330000000,
      "VariacionMensual": 0.04517,
      "VariacionAnual": 0.17418
    },
    {
      "CodigoPeriodo": "201102",
      "TipoDato": "Definitivo",
      "Indice": 88.4640000000,
      "VariacionMensual": 0.01295,
      "VariacionAnual": 0.18954
    },
    {
      "CodigoPeriodo": "201103",
      "TipoDato": "Definitivo",
      "Indice": 90.5860000000,
      "VariacionMensual": 0.02399,
      "VariacionAnual": 0.18853
    },
    {
      "CodigoPeriodo": "201104",
      "TipoDato": "Definitivo",
      "Indice": 92.0500000000,
      "VariacionMensual": 0.01616,
      "VariacionAnual": 0.17633
    },
    {
      "CodigoPeriodo": "201105",
      "TipoDato": "Definitivo",
      "Indice": 90.7550000000,
      "VariacionMensual": -0.01407,
      "VariacionAnual": 0.15062
    },
    {
      "CodigoPeriodo": "201106",
      "TipoDato": "Definitivo",
      "Indice": 90.2530000000,
      "VariacionMensual": -0.00553,
      "VariacionAnual": 0.15145
    },
    {
      "CodigoPeriodo": "201107",
      "TipoDato": "Definitivo",
      "Indice": 91.7050000000,
      "VariacionMensual": 0.01609,
      "VariacionAnual": 0.16029
    },
    {
      "CodigoPeriodo": "201108",
      "TipoDato": "Definitivo",
      "Indice": 90.8140000000,
      "VariacionMensual": -0.00972,
      "VariacionAnual": 0.15401
    },
    {
      "CodigoPeriodo": "201109",
      "TipoDato": "Definitivo",
      "Indice": 91.5810000000,
      "VariacionMensual": 0.00845,
      "VariacionAnual": 0.15921
    },
    {
      "CodigoPeriodo": "201110",
      "TipoDato": "Definitivo",
      "Indice": 91.9490000000,
      "VariacionMensual": 0.00402,
      "VariacionAnual": 0.14681
    },
    {
      "CodigoPeriodo": "201111",
      "TipoDato": "Definitivo",
      "Indice": 92.4370000000,
      "VariacionMensual": 0.00531,
      "VariacionAnual": 0.13746
    },
    {
      "CodigoPeriodo": "201112",
      "TipoDato": "Definitivo",
      "Indice": 92.2770000000,
      "VariacionMensual": -0.00173,
      "VariacionAnual": 0.10433
    },
    {
      "CodigoPeriodo": "201201",
      "TipoDato": "Definitivo",
      "Indice": 94.3290000000,
      "VariacionMensual": 0.02224,
      "VariacionAnual": 0.08011
    },
    {
      "CodigoPeriodo": "201202",
      "TipoDato": "Definitivo",
      "Indice": 95.3160000000,
      "VariacionMensual": 0.01046,
      "VariacionAnual": 0.07746
    },
    {
      "CodigoPeriodo": "201203",
      "TipoDato": "Definitivo",
      "Indice": 97.1830000000,
      "VariacionMensual": 0.01959,
      "VariacionAnual": 0.07283
    },
    {
      "CodigoPeriodo": "201204",
      "TipoDato": "Definitivo",
      "Indice": 99.7590000000,
      "VariacionMensual": 0.02651,
      "VariacionAnual": 0.08375
    },
    {
      "CodigoPeriodo": "201205",
      "TipoDato": "Definitivo",
      "Indice": 97.7960000000,
      "VariacionMensual": -0.01968,
      "VariacionAnual": 0.07758
    },
    {
      "CodigoPeriodo": "201206",
      "TipoDato": "Definitivo",
      "Indice": 95.3730000000,
      "VariacionMensual": -0.02478,
      "VariacionAnual": 0.05673
    },
    {
      "CodigoPeriodo": "201207",
      "TipoDato": "Definitivo",
      "Indice": 98.0270000000,
      "VariacionMensual": 0.02783,
      "VariacionAnual": 0.06894
    },
    {
      "CodigoPeriodo": "201208",
      "TipoDato": "Definitivo",
      "Indice": 101.0170000000,
      "VariacionMensual": 0.03050,
      "VariacionAnual": 0.11235
    },
    {
      "CodigoPeriodo": "201209",
      "TipoDato": "Definitivo",
      "Indice": 103.2030000000,
      "VariacionMensual": 0.02164,
      "VariacionAnual": 0.12690
    },
    {
      "CodigoPeriodo": "201210",
      "TipoDato": "Definitivo",
      "Indice": 101.4380000000,
      "VariacionMensual": -0.01710,
      "VariacionAnual": 0.10320
    },
    {
      "CodigoPeriodo": "201211",
      "TipoDato": "Definitivo",
      "Indice": 98.6830000000,
      "VariacionMensual": -0.02716,
      "VariacionAnual": 0.06757
    },
    {
      "CodigoPeriodo": "201212",
      "TipoDato": "Definitivo",
      "Indice": 98.4210000000,
      "VariacionMensual": -0.00265,
      "VariacionAnual": 0.06658
    },
    {
      "CodigoPeriodo": "201301",
      "TipoDato": "Definitivo",
      "Indice": 99.4080000000,
      "VariacionMensual": 0.01003,
      "VariacionAnual": 0.05384
    },
    {
      "CodigoPeriodo": "201302",
      "TipoDato": "Definitivo",
      "Indice": 101.3100000000,
      "VariacionMensual": 0.01913,
      "VariacionAnual": 0.06289
    },
    {
      "CodigoPeriodo": "201303",
      "TipoDato": "Definitivo",
      "Indice": 100.6060000000,
      "VariacionMensual": -0.00695,
      "VariacionAnual": 0.03522
    },
    {
      "CodigoPeriodo": "201304",
      "TipoDato": "Definitivo",
      "Indice": 97.8360000000,
      "VariacionMensual": -0.02753,
      "VariacionAnual": -0.01928
    },
    {
      "CodigoPeriodo": "201305",
      "TipoDato": "Definitivo",
      "Indice": 96.7110000000,
      "VariacionMensual": -0.01150,
      "VariacionAnual": -0.01109
    },
    {
      "CodigoPeriodo": "201306",
      "TipoDato": "Definitivo",
      "Indice": 97.0120000000,
      "VariacionMensual": 0.00311,
      "VariacionAnual": 0.01719
    },
    {
      "CodigoPeriodo": "201307",
      "TipoDato": "Definitivo",
      "Indice": 98.6580000000,
      "VariacionMensual": 0.01697,
      "VariacionAnual": 0.00644
    },
    {
      "CodigoPeriodo": "201308",
      "TipoDato": "Definitivo",
      "Indice": 99.7600000000,
      "VariacionMensual": 0.01117,
      "VariacionAnual": -0.01244
    },
    {
      "CodigoPeriodo": "201309",
      "TipoDato": "Definitivo",
      "Indice": 100.3380000000,
      "VariacionMensual": 0.00579,
      "VariacionAnual": -0.02776
    },
    {
      "CodigoPeriodo": "201310",
      "TipoDato": "Definitivo",
      "Indice": 99.5200000000,
      "VariacionMensual": -0.00815,
      "VariacionAnual": -0.01891
    },
    {
      "CodigoPeriodo": "201311",
      "TipoDato": "Definitivo",
      "Indice": 98.7390000000,
      "VariacionMensual": -0.00785,
      "VariacionAnual": 0.00057
    },
    {
      "CodigoPeriodo": "201312",
      "TipoDato": "Definitivo",
      "Indice": 99.4460000000,
      "VariacionMensual": 0.00716,
      "VariacionAnual": 0.01041
    },
    {
      "CodigoPeriodo": "201401",
      "TipoDato": "Definitivo",
      "Indice": 99.1630000000,
      "VariacionMensual": -0.00285,
      "VariacionAnual": -0.00246
    },
    {
      "CodigoPeriodo": "201402",
      "TipoDato": "Definitivo",
      "Indice": 99.1280000000,
      "VariacionMensual": -0.00035,
      "VariacionAnual": -0.02154
    },
    {
      "CodigoPeriodo": "201403",
      "TipoDato": "Definitivo",
      "Indice": 98.7610000000,
      "VariacionMensual": -0.00370,
      "VariacionAnual": -0.01834
    },
    {
      "CodigoPeriodo": "201404",
      "TipoDato": "Definitivo",
      "Indice": 99.3170000000,
      "VariacionMensual": 0.00563,
      "VariacionAnual": 0.01514
    },
    {
      "CodigoPeriodo": "201405",
      "TipoDato": "Definitivo",
      "Indice": 99.6110000000,
      "VariacionMensual": 0.00296,
      "VariacionAnual": 0.02999
    },
    {
      "CodigoPeriodo": "201406",
      "TipoDato": "Definitivo",
      "Indice": 99.6810000000,
      "VariacionMensual": 0.00070,
      "VariacionAnual": 0.02751
    },
    {
      "CodigoPeriodo": "201407",
      "TipoDato": "Definitivo",
      "Indice": 99.0430000000,
      "VariacionMensual": -0.00640,
      "VariacionAnual": 0.00390
    },
    {
      "CodigoPeriodo": "201408",
      "TipoDato": "Definitivo",
      "Indice": 98.9380000000,
      "VariacionMensual": -0.00106,
      "VariacionAnual": -0.00824
    },
    {
      "CodigoPeriodo": "201409",
      "TipoDato": "Definitivo",
      "Indice": 100.3080000000,
      "VariacionMensual": 0.01385,
      "VariacionAnual": -0.00030
    },
    {
      "CodigoPeriodo": "201410",
      "TipoDato": "Definitivo",
      "Indice": 98.4040000000,
      "VariacionMensual": -0.01898,
      "VariacionAnual": -0.01121
    },
    {
      "CodigoPeriodo": "201411",
      "TipoDato": "Definitivo",
      "Indice": 95.5860000000,
      "VariacionMensual": -0.02864,
      "VariacionAnual": -0.03193
    },
    {
      "CodigoPeriodo": "201412",
      "TipoDato": "Definitivo",
      "Indice": 91.1290000000,
      "VariacionMensual": -0.04663,
      "VariacionAnual": -0.08363
    },
    {
      "CodigoPeriodo": "201501",
      "TipoDato": "Definitivo",
      "Indice": 88.4030000000,
      "VariacionMensual": -0.02991,
      "VariacionAnual": -0.10851
    },
    {
      "CodigoPeriodo": "201502",
      "TipoDato": "Definitivo",
      "Indice": 89.7600000000,
      "VariacionMensual": 0.01535,
      "VariacionAnual": -0.09450
    },
    {
      "CodigoPeriodo": "201503",
      "TipoDato": "Definitivo",
      "Indice": 91.9030000000,
      "VariacionMensual": 0.02387,
      "VariacionAnual": -0.06944
    },
    {
      "CodigoPeriodo": "201504",
      "TipoDato": "Definitivo",
      "Indice": 92.3590000000,
      "VariacionMensual": 0.00496,
      "VariacionAnual": -0.07006
    },
    {
      "CodigoPeriodo": "201505",
      "TipoDato": "Definitivo",
      "Indice": 93.2080000000,
      "VariacionMensual": 0.00919,
      "VariacionAnual": -0.06428
    },
    {
      "CodigoPeriodo": "201506",
      "TipoDato": "Definitivo",
      "Indice": 93.8470000000,
      "VariacionMensual": 0.00686,
      "VariacionAnual": -0.05853
    },
    {
      "CodigoPeriodo": "201507",
      "TipoDato": "Definitivo",
      "Indice": 93.2070000000,
      "VariacionMensual": -0.00682,
      "VariacionAnual": -0.05892
    },
    {
      "CodigoPeriodo": "201508",
      "TipoDato": "Definitivo",
      "Indice": 89.1220000000,
      "VariacionMensual": -0.04383,
      "VariacionAnual": -0.09921
    },
    {
      "CodigoPeriodo": "201509",
      "TipoDato": "Definitivo",
      "Indice": 86.5900000000,
      "VariacionMensual": -0.02841,
      "VariacionAnual": -0.13676
    },
    {
      "CodigoPeriodo": "201510",
      "TipoDato": "Definitivo",
      "Indice": 85.5570000000,
      "VariacionMensual": -0.01193,
      "VariacionAnual": -0.13055
    },
    {
      "CodigoPeriodo": "201511",
      "TipoDato": "Definitivo",
      "Indice": 86.1860000000,
      "VariacionMensual": 0.00735,
      "VariacionAnual": -0.09834
    },
    {
      "CodigoPeriodo": "201512",
      "TipoDato": "Definitivo",
      "Indice": 84.3310000000,
      "VariacionMensual": -0.02152,
      "VariacionAnual": -0.07460
    },
    {
      "CodigoPeriodo": "201601",
      "TipoDato": "Definitivo",
      "Indice": 78.9010000000,
      "VariacionMensual": -0.06439,
      "VariacionAnual": -0.10749
    },
    {
      "CodigoPeriodo": "201602",
      "TipoDato": "Definitivo",
      "Indice": 76.5160000000,
      "VariacionMensual": -0.03023,
      "VariacionAnual": -0.14755
    },
    {
      "CodigoPeriodo": "201603",
      "TipoDato": "Definitivo",
      "Indice": 77.9600000000,
      "VariacionMensual": 0.01887,
      "VariacionAnual": -0.15171
    },
    {
      "CodigoPeriodo": "201604",
      "TipoDato": "Definitivo",
      "Indice": 78.0700000000,
      "VariacionMensual": 0.00141,
      "VariacionAnual": -0.15471
    },
    {
      "CodigoPeriodo": "201605",
      "TipoDato": "Definitivo",
      "Indice": 79.9400000000,
      "VariacionMensual": 0.02395,
      "VariacionAnual": -0.14235
    },
    {
      "CodigoPeriodo": "201606",
      "TipoDato": "Definitivo",
      "Indice": 82.8200000000,
      "VariacionMensual": 0.03603,
      "VariacionAnual": -0.11750
    },
    {
      "CodigoPeriodo": "201607",
      "TipoDato": "Definitivo",
      "Indice": 82.0170000000,
      "VariacionMensual": -0.00970,
      "VariacionAnual": -0.12006
    },
    {
      "CodigoPeriodo": "201608",
      "TipoDato": "Definitivo",
      "Indice": 81.2540000000,
      "VariacionMensual": -0.00930,
      "VariacionAnual": -0.08828
    },
    {
      "CodigoPeriodo": "201609",
      "TipoDato": "Definitivo",
      "Indice": 82.3740000000,
      "VariacionMensual": 0.01378,
      "VariacionAnual": -0.04869
    },
    {
      "CodigoPeriodo": "201610",
      "TipoDato": "Definitivo",
      "Indice": 85.5950000000,
      "VariacionMensual": 0.03910,
      "VariacionAnual": 0.00044
    },
    {
      "CodigoPeriodo": "201611",
      "TipoDato": "Definitivo",
      "Indice": 85.5260000000,
      "VariacionMensual": -0.00081,
      "VariacionAnual": -0.00766
    },
    {
      "CodigoPeriodo": "201612",
      "TipoDato": "Definitivo",
      "Indice": 88.7710000000,
      "VariacionMensual": 0.03794,
      "VariacionAnual": 0.05265
    },
    {
      "CodigoPeriodo": "201701",
      "TipoDato": "Definitivo",
      "Indice": 92.9840000000,
      "VariacionMensual": 0.04746,
      "VariacionAnual": 0.17849
    },
    {
      "CodigoPeriodo": "201702",
      "TipoDato": "Definitivo",
      "Indice": 89.9190000000,
      "VariacionMensual": -0.03296,
      "VariacionAnual": 0.17517
    },
    {
      "CodigoPeriodo": "201703",
      "TipoDato": "Definitivo",
      "Indice": 87.4660000000,
      "VariacionMensual": -0.02728,
      "VariacionAnual": 0.12193
    },
    {
      "CodigoPeriodo": "201704",
      "TipoDato": "Definitivo",
      "Indice": 87.7770000000,
      "VariacionMensual": 0.00356,
      "VariacionAnual": 0.12434
    },
    {
      "CodigoPeriodo": "201705",
      "TipoDato": "Definitivo",
      "Indice": 86.6570000000,
      "VariacionMensual": -0.01276,
      "VariacionAnual": 0.08403
    },
    {
      "CodigoPeriodo": "201706",
      "TipoDato": "Definitivo",
      "Indice": 85.7640000000,
      "VariacionMensual": -0.01030,
      "VariacionAnual": 0.03555
    },
    {
      "CodigoPeriodo": "201707",
      "TipoDato": "Definitivo",
      "Indice": 84.9980000000,
      "VariacionMensual": -0.00893,
      "VariacionAnual": 0.03635
    },
    {
      "CodigoPeriodo": "201708",
      "TipoDato": "Definitivo",
      "Indice": 85.8650000000,
      "VariacionMensual": 0.01020,
      "VariacionAnual": 0.05675
    },
    {
      "CodigoPeriodo": "201709",
      "TipoDato": "Definitivo",
      "Indice": 86.8470000000,
      "VariacionMensual": 0.01144,
      "VariacionAnual": 0.05430
    },
    {
      "CodigoPeriodo": "201710",
      "TipoDato": "Definitivo",
      "Indice": 88.7840000000,
      "VariacionMensual": 0.02230,
      "VariacionAnual": 0.03726
    },
    {
      "CodigoPeriodo": "201711",
      "TipoDato": "Definitivo",
      "Indice": 90.4590000000,
      "VariacionMensual": 0.01887,
      "VariacionAnual": 0.05768
    },
    {
      "CodigoPeriodo": "201712",
      "TipoDato": "Definitivo",
      "Indice": 90.8200000000,
      "VariacionMensual": 0.00399,
      "VariacionAnual": 0.02308
    },
    {
      "CodigoPeriodo": "201801",
      "TipoDato": "Definitivo",
      "Indice": 91.2420000000,
      "VariacionMensual": 0.00465,
      "VariacionAnual": -0.01873
    },
    {
      "CodigoPeriodo": "201802",
      "TipoDato": "Definitivo",
      "Indice": 90.5950000000,
      "VariacionMensual": -0.00709,
      "VariacionAnual": 0.00752
    },
    {
      "CodigoPeriodo": "201803",
      "TipoDato": "Definitivo",
      "Indice": 88.3280000000,
      "VariacionMensual": -0.02502,
      "VariacionAnual": 0.00986
    },
    {
      "CodigoPeriodo": "201804",
      "TipoDato": "Definitivo",
      "Indice": 89.6650000000,
      "VariacionMensual": 0.01514,
      "VariacionAnual": 0.02151
    },
    {
      "CodigoPeriodo": "201805",
      "TipoDato": "Definitivo",
      "Indice": 93.2350000000,
      "VariacionMensual": 0.03981,
      "VariacionAnual": 0.07591
    },
    {
      "CodigoPeriodo": "201806",
      "TipoDato": "Definitivo",
      "Indice": 94.1100000000,
      "VariacionMensual": 0.00938,
      "VariacionAnual": 0.09731
    },
    {
      "CodigoPeriodo": "201807",
      "TipoDato": "Definitivo",
      "Indice": 94.6240000000,
      "VariacionMensual": 0.00546,
      "VariacionAnual": 0.11325
    },
    {
      "CodigoPeriodo": "201808",
      "TipoDato": "Definitivo",
      "Indice": 95.3590000000,
      "VariacionMensual": 0.00777,
      "VariacionAnual": 0.11057
    },
    {
      "CodigoPeriodo": "201809",
      "TipoDato": "Definitivo",
      "Indice": 97.0460000000,
      "VariacionMensual": 0.01769,
      "VariacionAnual": 0.11744
    },
    {
      "CodigoPeriodo": "201810",
      "TipoDato": "Definitivo",
      "Indice": 98.0420000000,
      "VariacionMensual": 0.01026,
      "VariacionAnual": 0.10428
    },
    {
      "CodigoPeriodo": "201811",
      "TipoDato": "Definitivo",
      "Indice": 96.4340000000,
      "VariacionMensual": -0.01640,
      "VariacionAnual": 0.06605
    },
    {
      "CodigoPeriodo": "201812",
      "TipoDato": "Definitivo",
      "Indice": 92.8680000000,
      "VariacionMensual": -0.03698,
      "VariacionAnual": 0.02255
    },
    {
      "CodigoPeriodo": "201901",
      "TipoDato": "Definitivo",
      "Indice": 92.2970000000,
      "VariacionMensual": -0.00615,
      "VariacionAnual": 0.01156
    },
    {
      "CodigoPeriodo": "201902",
      "TipoDato": "Definitivo",
      "Indice": 92.7030000000,
      "VariacionMensual": 0.00440,
      "VariacionAnual": 0.02327
    },
    {
      "CodigoPeriodo": "201903",
      "TipoDato": "Definitivo",
      "Indice": 92.9750000000,
      "VariacionMensual": 0.00293,
      "VariacionAnual": 0.05261
    },
    {
      "CodigoPeriodo": "201904",
      "TipoDato": "Definitivo",
      "Indice": 94.3200000000,
      "VariacionMensual": 0.01447,
      "VariacionAnual": 0.05192
    },
    {
      "CodigoPeriodo": "201905",
      "TipoDato": "Definitivo",
      "Indice": 94.7520000000,
      "VariacionMensual": 0.00458,
      "VariacionAnual": 0.01627
    },
    {
      "CodigoPeriodo": "201906",
      "TipoDato": "Definitivo",
      "Indice": 92.1310000000,
      "VariacionMensual": -0.02766,
      "VariacionAnual": -0.02103
    },
    {
      "CodigoPeriodo": "201907",
      "TipoDato": "Definitivo",
      "Indice": 92.7590000000,
      "VariacionMensual": 0.00682,
      "VariacionAnual": -0.01971
    },
    {
      "CodigoPeriodo": "201908",
      "TipoDato": "Definitivo",
      "Indice": 91.3940000000,
      "VariacionMensual": -0.01472,
      "VariacionAnual": -0.04158
    },
    {
      "CodigoPeriodo": "201909",
      "TipoDato": "Definitivo",
      "Indice": 90.9480000000,
      "VariacionMensual": -0.00488,
      "VariacionAnual": -0.06284
    },
    {
      "CodigoPeriodo": "201910",
      "TipoDato": "Definitivo",
      "Indice": 91.9900000000,
      "VariacionMensual": 0.01146,
      "VariacionAnual": -0.06173
    },
    {
      "CodigoPeriodo": "201911",
      "TipoDato": "Definitivo",
      "Indice": 91.5490000000,
      "VariacionMensual": -0.00479,
      "VariacionAnual": -0.05066
    },
    {
      "CodigoPeriodo": "201912",
      "TipoDato": "Definitivo",
      "Indice": 90.8420000000,
      "VariacionMensual": -0.00772,
      "VariacionAnual": -0.02182
    },
    {
      "CodigoPeriodo": "202001",
      "TipoDato": "Definitivo",
      "Indice": 92.1780000000,
      "VariacionMensual": 0.01471,
      "VariacionAnual": -0.00129
    },
    {
      "CodigoPeriodo": "202002",
      "TipoDato": "Definitivo",
      "Indice": 89.5690000000,
      "VariacionMensual": -0.02830,
      "VariacionAnual": -0.03381
    },
    {
      "CodigoPeriodo": "202003",
      "TipoDato": "Definitivo",
      "Indice": 83.6140000000,
      "VariacionMensual": -0.06649,
      "VariacionAnual": -0.10068
    },
    {
      "CodigoPeriodo": "202004",
      "TipoDato": "Definitivo",
      "Indice": 77.5320000000,
      "VariacionMensual": -0.07274,
      "VariacionAnual": -0.17799
    },
    {
      "CodigoPeriodo": "202005",
      "TipoDato": "Definitivo",
      "Indice": 76.9210000000,
      "VariacionMensual": -0.00788,
      "VariacionAnual": -0.18819
    },
    {
      "CodigoPeriodo": "202006",
      "TipoDato": "Definitivo",
      "Indice": 80.0700000000,
      "VariacionMensual": 0.04094,
      "VariacionAnual": -0.13091
    },
    {
      "CodigoPeriodo": "202007",
      "TipoDato": "Definitivo",
      "Indice": 81.6860000000,
      "VariacionMensual": 0.02018,
      "VariacionAnual": -0.11937
    },
    {
      "CodigoPeriodo": "202008",
      "TipoDato": "Definitivo",
      "Indice": 81.9710000000,
      "VariacionMensual": 0.00349,
      "VariacionAnual": -0.10310
    },
    {
      "CodigoPeriodo": "202009",
      "TipoDato": "Definitivo",
      "Indice": 82.2300000000,
      "VariacionMensual": 0.00316,
      "VariacionAnual": -0.09586
    },
    {
      "CodigoPeriodo": "202010",
      "TipoDato": "Definitivo",
      "Indice": 80.6760000000,
      "VariacionMensual": -0.01890,
      "VariacionAnual": -0.12299
    },
    {
      "CodigoPeriodo": "202011",
      "TipoDato": "Definitivo",
      "Indice": 81.6900000000,
      "VariacionMensual": 0.01257,
      "VariacionAnual": -0.10769
    },
    {
      "CodigoPeriodo": "202012",
      "TipoDato": "Definitivo",
      "Indice": 83.9440000000,
      "VariacionMensual": 0.02759,
      "VariacionAnual": -0.07593
    },
    {
      "CodigoPeriodo": "202101",
      "TipoDato": "Definitivo",
      "Indice": 89.5200000000,
      "VariacionMensual": 0.06643,
      "VariacionAnual": -0.02884
    },
    {
      "CodigoPeriodo": "202102",
      "TipoDato": "Definitivo",
      "Indice": 85.1060000000,
      "VariacionMensual": -0.04931,
      "VariacionAnual": -0.04983
    },
    {
      "CodigoPeriodo": "202103",
      "TipoDato": "Definitivo",
      "Indice": 90.5510000000,
      "VariacionMensual": 0.06398,
      "VariacionAnual": 0.08296
    },
    {
      "CodigoPeriodo": "202104",
      "TipoDato": "Definitivo",
      "Indice": 94.1800000000,
      "VariacionMensual": 0.04008,
      "VariacionAnual": 0.21472
    },
    {
      "CodigoPeriodo": "202105",
      "TipoDato": "Definitivo",
      "Indice": 95.5020000000,
      "VariacionMensual": 0.01404,
      "VariacionAnual": 0.24156
    },
    {
      "CodigoPeriodo": "202106",
      "TipoDato": "Definitivo",
      "Indice": 98.7870000000,
      "VariacionMensual": 0.03440,
      "VariacionAnual": 0.23376
    },
    {
      "CodigoPeriodo": "202107",
      "TipoDato": "Definitivo",
      "Indice": 98.5470000000,
      "VariacionMensual": -0.00243,
      "VariacionAnual": 0.20641
    },
    {
      "CodigoPeriodo": "202108",
      "TipoDato": "Definitivo",
      "Indice": 100.9850000000,
      "VariacionMensual": 0.02474,
      "VariacionAnual": 0.23196
    },
    {
      "CodigoPeriodo": "202109",
      "TipoDato": "Definitivo",
      "Indice": 105.6540000000,
      "VariacionMensual": 0.04623,
      "VariacionAnual": 0.28486
    },
    {
      "CodigoPeriodo": "202110",
      "TipoDato": "Definitivo",
      "Indice": 112.5750000000,
      "VariacionMensual": 0.06551,
      "VariacionAnual": 0.39540
    },
    {
      "CodigoPeriodo": "202111",
      "TipoDato": "Definitivo",
      "Indice": 110.9980000000,
      "VariacionMensual": -0.01401,
      "VariacionAnual": 0.35877
    },
    {
      "CodigoPeriodo": "202112",
      "TipoDato": "Definitivo",
      "Indice": 117.5940000000,
      "VariacionMensual": 0.05942,
      "VariacionAnual": 0.40086
    },
    {
      "CodigoPeriodo": "202201",
      "TipoDato": "Definitivo",
      "Indice": 119.2040000000,
      "VariacionMensual": 0.01369,
      "VariacionAnual": 0.33159
    },
    {
      "CodigoPeriodo": "202202",
      "TipoDato": "Definitivo",
      "Indice": 123.3390000000,
      "VariacionMensual": 0.03469,
      "VariacionAnual": 0.44924
    },
    {
      "CodigoPeriodo": "202203",
      "TipoDato": "Definitivo",
      "Indice": 146.5110000000,
      "VariacionMensual": 0.18787,
      "VariacionAnual": 0.61799
    },
    {
      "CodigoPeriodo": "202204",
      "TipoDato": "Definitivo",
      "Indice": 127.3530000000,
      "VariacionMensual": -0.13076,
      "VariacionAnual": 0.35223
    },
    {
      "CodigoPeriodo": "202205",
      "TipoDato": "Definitivo",
      "Indice": 129.7600000000,
      "VariacionMensual": 0.01890,
      "VariacionAnual": 0.35872
    },
    {
      "CodigoPeriodo": "202206",
      "TipoDato": "Definitivo",
      "Indice": 141.1360000000,
      "VariacionMensual": 0.08767,
      "VariacionAnual": 0.42869
    },
    {
      "CodigoPeriodo": "202207",
      "TipoDato": "Definitivo",
      "Indice": 141.1810000000,
      "VariacionMensual": 0.00032,
      "VariacionAnual": 0.43263
    },
    {
      "CodigoPeriodo": "202208",
      "TipoDato": "Definitivo",
      "Indice": 140.5200000000,
      "VariacionMensual": -0.00468,
      "VariacionAnual": 0.39149
    },
    {
      "CodigoPeriodo": "202209",
      "TipoDato": "Definitivo",
      "Indice": 131.1880000000,
      "VariacionMensual": -0.06641,
      "VariacionAnual": 0.24168
    },
    {
      "CodigoPeriodo": "202210",
      "TipoDato": "Definitivo",
      "Indice": 123.6460000000,
      "VariacionMensual": -0.05749,
      "VariacionAnual": 0.09834
    },
    {
      "CodigoPeriodo": "202211",
      "TipoDato": "Definitivo",
      "Indice": 117.8690000000,
      "VariacionMensual": -0.04672,
      "VariacionAnual": 0.06190
    },
    {
      "CodigoPeriodo": "202212",
      "TipoDato": "Definitivo",
      "Indice": 110.8970000000,
      "VariacionMensual": -0.05915,
      "VariacionAnual": -0.05695
    },
    {
      "CodigoPeriodo": "202301",
      "TipoDato": "Definitivo",
      "Indice": 110.9560000000,
      "VariacionMensual": 0.00053,
      "VariacionAnual": -0.06919
    },
    {
      "CodigoPeriodo": "202302",
      "TipoDato": "Definitivo",
      "Indice": 113.8160000000,
      "VariacionMensual": 0.02578,
      "VariacionAnual": -0.07721
    },
    {
      "CodigoPeriodo": "202303",
      "TipoDato": "Definitivo",
      "Indice": 110.2720000000,
      "VariacionMensual": -0.03114,
      "VariacionAnual": -0.24735
    },
    {
      "CodigoPeriodo": "202304",
      "TipoDato": "Definitivo",
      "Indice": 107.8680000000,
      "VariacionMensual": -0.02180,
      "VariacionAnual": -0.15300
    },
    {
      "CodigoPeriodo": "202305",
      "TipoDato": "Definitivo",
      "Indice": 104.4390000000,
      "VariacionMensual": -0.03179,
      "VariacionAnual": -0.19514
    },
    {
      "CodigoPeriodo": "202306",
      "TipoDato": "Definitivo",
      "Indice": 106.2790000000,
      "VariacionMensual": 0.01762,
      "VariacionAnual": -0.24697
    },
    {
      "CodigoPeriodo": "202307",
      "TipoDato": "Definitivo",
      "Indice": 107.4530000000,
      "VariacionMensual": 0.01105,
      "VariacionAnual": -0.23890
    },
    {
      "CodigoPeriodo": "202308",
      "TipoDato": "Definitivo",
      "Indice": 111.2430000000,
      "VariacionMensual": 0.03527,
      "VariacionAnual": -0.20835
    },
    {
      "CodigoPeriodo": "202309",
      "TipoDato": "Definitivo",
      "Indice": 113.6550000000,
      "VariacionMensual": 0.02168,
      "VariacionAnual": -0.13365
    },
    {
      "CodigoPeriodo": "202310",
      "TipoDato": "Definitivo",
      "Indice": 111.1770000000,
      "VariacionMensual": -0.02180,
      "VariacionAnual": -0.10084
    },
    {
      "CodigoPeriodo": "202311",
      "TipoDato": "Definitivo",
      "Indice": 106.4630000000,
      "VariacionMensual": -0.04240,
      "VariacionAnual": -0.09677
    },
    {
      "CodigoPeriodo": "202312",
      "TipoDato": "Definitivo",
      "Indice": 104.7320000000,
      "VariacionMensual": -0.01626,
      "VariacionAnual": -0.05559
    },
    {
      "CodigoPeriodo": "202401",
      "TipoDato": "Definitivo",
      "Indice": 108.8500000000,
      "VariacionMensual": 0.03932,
      "VariacionAnual": -0.01898
    },
    {
      "CodigoPeriodo": "202402",
      "TipoDato": "Definitivo",
      "Indice": 108.7590000000,
      "VariacionMensual": -0.00084,
      "VariacionAnual": -0.04443
    },
    {
      "CodigoPeriodo": "202403",
      "TipoDato": "Definitivo",
      "Indice": 111.8320000000,
      "VariacionMensual": 0.02826,
      "VariacionAnual": 0.01415
    },
    {
      "CodigoPeriodo": "202404",
      "TipoDato": "Definitivo",
      "Indice": 113.3660000000,
      "VariacionMensual": 0.01372,
      "VariacionAnual": 0.05097
    },
    {
      "CodigoPeriodo": "202405",
      "TipoDato": "Definitivo",
      "Indice": 113.0300000000,
      "VariacionMensual": -0.00296,
      "VariacionAnual": 0.08226
    },
    {
      "CodigoPeriodo": "202406",
      "TipoDato": "Definitivo",
      "Indice": 112.9730000000,
      "VariacionMensual": -0.00050,
      "VariacionAnual": 0.06299
    },
    {
      "CodigoPeriodo": "202407",
      "TipoDato": "Definitivo",
      "Indice": 110.3740000000,
      "VariacionMensual": -0.02301,
      "VariacionAnual": 0.02718
    },
    {
      "CodigoPeriodo": "202408",
      "TipoDato": "Definitivo",
      "Indice": 109.6280000000,
      "VariacionMensual": -0.00676,
      "VariacionAnual": -0.01452
    },
    {
      "CodigoPeriodo": "202409",
      "TipoDato": "Definitivo",
      "Indice": 106.5090000000,
      "VariacionMensual": -0.02845,
      "VariacionAnual": -0.06287
    },
    {
      "CodigoPeriodo": "202410",
      "TipoDato": "Definitivo",
      "Indice": 107.1270000000,
      "VariacionMensual": 0.00580,
      "VariacionAnual": -0.03643
    },
    {
      "CodigoPeriodo": "202411",
      "TipoDato": "Definitivo",
      "Indice": 109.4520000000,
      "VariacionMensual": 0.02170,
      "VariacionAnual": 0.02808
    },
    {
      "CodigoPeriodo": "202412",
      "TipoDato": "Definitivo",
      "Indice": 110.7610000000,
      "VariacionMensual": 0.01196,
      "VariacionAnual": 0.05757
    },
    {
      "CodigoPeriodo": "202501",
      "TipoDato": "Definitivo",
      "Indice": 117.7990000000,
      "VariacionMensual": 0.06354,
      "VariacionAnual": 0.08221
    },
    {
      "CodigoPeriodo": "202502",
      "TipoDato": "Definitivo",
      "Indice": 118.4700000000,
      "VariacionMensual": 0.00570,
      "VariacionAnual": 0.08929
    },
    {
      "CodigoPeriodo": "202503",
      "TipoDato": "Definitivo",
      "Indice": 114.0780000000,
      "VariacionMensual": -0.03707,
      "VariacionAnual": 0.02008
    },
    {
      "CodigoPeriodo": "202504",
      "TipoDato": "Definitivo",
      "Indice": 110.7790000000,
      "VariacionMensual": -0.02892,
      "VariacionAnual": -0.02282
    },
    {
      "CodigoPeriodo": "202505",
      "TipoDato": "Definitivo",
      "Indice": 110.0020000000,
      "VariacionMensual": -0.00701,
      "VariacionAnual": -0.02679
    },
    {
      "CodigoPeriodo": "202506",
      "TipoDato": "Definitivo",
      "Indice": 112.0770000000,
      "VariacionMensual": 0.01886,
      "VariacionAnual": -0.00793
    },
    {
      "CodigoPeriodo": "202507",
      "TipoDato": "Definitivo",
      "Indice": 113.9700000000,
      "VariacionMensual": 0.01689,
      "VariacionAnual": 0.03258
    },
    {
      "CodigoPeriodo": "202508",
      "TipoDato": "Definitivo",
      "Indice": 113.6870000000,
      "VariacionMensual": -0.00248,
      "VariacionAnual": 0.03703
    },
    {
      "CodigoPeriodo": "202509",
      "TipoDato": "Definitivo",
      "Indice": 113.4000000000,
      "VariacionMensual": -0.00252,
      "VariacionAnual": 0.06470
    }
  ]
}